emoji_data/.gitignore
emoji_data/__init__.py
emoji_data/_version.py
emoji_data/character.py
emoji_data/container.py
emoji_data/definitions.py
emoji_data/helpers.py
emoji_data/py.typed
emoji_data/sequence.py
emoji_data/utils.py
emoji_data/version.py
emoji_data/data/.gitignore
emoji_data/data/README
emoji_data/data/emoji-data.txt
emoji_data/data/emoji-sequences.txt
emoji_data/data/emoji-test.txt
emoji_data/data/emoji-variation-sequences.txt
emoji_data/data/emoji-zwj-sequences.txt
emoji_data-0.5.0.dist-info/licenses/LICENSE.txt
emoji_data-0.5.0.dist-info/METADATA
emoji_data-0.5.0.dist-info/WHEEL
emoji_data-0.5.0.dist-info/top_level.txt
emoji_data-0.5.0.dist-info/RECORD
