Metadata-Version: 2.4
Name: emoji-data
Version: 0.5.0
Summary: A library that represents emoji sequences and characters based on the Unicode® Technical Standard #51 Data Files
Author-email: liu xue yan <liu_xue_yan@foxmail.com>
License-Expression: GPL-3.0-or-later
Project-URL: homepage, https://github.com/tanbro/emoji-data
Project-URL: repository, https://github.com/tanbro/emoji-data.git
Keywords: emoji,unicode
Classifier: Development Status :: 5 - Production/Stable
Classifier: Intended Audience :: Developers
Classifier: Topic :: Text Processing
Classifier: Programming Language :: Python
Requires-Python: >=3.9
License-File: LICENSE.txt
Requires-Dist: importlib-resources; python_version < "3.9"
Dynamic: license-file
